{ "compressionlevel":-1,
 "height":20,
 "infinite":false,
 "layers":[
        {
         "data":[0, 0, 0, 0, 0, 0, 0, 0, 0, 0, 0, 1061, 0, 0, 1060, 0, 0, 0, 0, 1058,
            1061, 0, 1061, 1061, 1061, 1061, 0, 1061, 1058, 1061, 0, 0, 1061, 1061, 1060, 1060, 1061, 1061, 1061, 0,
            1062, 0, 0, 1061, 0, 0, 1061, 1060, 1059, 0, 987, 0, 1061, 0, 1061, 0, 1062, 1061, 0, 0,
            0, 1059, 0, 1058, 1061, 0, 10803, 10803, 10803, 10803, 10803, 10803, 10803, 0, 1061, 0, 0, 1059, 1061, 0,
            1059, 0, 1060, 1061, 0, 10803, 479, 480, 477, 477, 0, 478, 477, 0, 0, 1061, 1060, 1060, 0, 0,
            1059, 0, 1060, 0, 10940, 477, 480, 479, 477, 480, 479, 477, 479, 478, 0, 0, 1061, 0, 988, 0,
            1059, 0, 0, 10803, 478, 479, 477, 477, 477, 479, 479, 478, 480, 480, 479, 0, 10803, 0, 0, 0,
            0, 0, 1063, 479, 479, 479, 478, 480, 479, 478, 480, 477, 477, 479, 479, 477, 10803, 1059, 1058, 0,
            1061, 0, 1063, 477, 477, 478, 479, 0, 480, 479, 479, 479, 478, 478, 479, 479, 10803, 0, 0, 1063,
            1061, 0, 0, 477, 478, 480, 480, 477, 480, 478, 480, 477, 478, 480, 477, 479, 10803, 1059, 0, 0,
            10374, 996, 0, 479, 478, 10803, 478, 480, 479, 479, 479, 479, 0, 478, 478, 478, 10803, 0, 1060, 1063,
            0, 0, 0, 480, 478, 0, 479, 480, 477, 478, 478, 479, 477, 479, 480, 478, 10803, 1063, 1059, 0,
            1063, 0, 1063, 480, 477, 478, 479, 480, 478, 477, 477, 477, 479, 480, 479, 480, 10803, 0, 0, 1058,
            1062, 0, 0, 478, 479, 0, 0, 477, 480, 477, 480, 478, 479, 477, 480, 480, 10803, 1063, 1063, 0,
            0, 1059, 0, 0, 479, 479, 0, 8058, 480, 0, 477, 478, 0, 480, 477, 478, 0, 0, 0, 0,
            1061, 0, 1059, 0, 0, 478, 0, 0, 477, 0, 480, 479, 480, 478, 479, 0, 1065, 1058, 1063, 0,
            0, 1061, 0, 1062, 0, 0, 8058, 477, 478, 477, 478, 477, 479, 479, 0, 1065, 1059, 1061, 1061, 0,
            1059, 0, 0, 0, 1061, 0, 0, 0, 0, 0, 0, 0, 0, 0, 1065, 1059, 1061, 1061, 1063, 0,
            1062, 1059, 1065, 0, 1063, 0, 1065, 1060, 1061, 1061, 0, 1059, 1065, 0, 1065, 0, 0, 0, 1060, 0,
            1065, 1063, 0, 1060, 0, 1063, 0, 1059, 1065, 1059, 1058, 1065, 0, 1065, 1061, 0, 994, 0, 1063, 0],
         "height":20,
         "id":1,
         "name":"ground",
         "opacity":1,
         "type":"tilelayer",
         "visible":true,
         "width":20,
         "x":0,
         "y":0
        }, 
        {
         "data":[0, 0, 0, 0, 0, 0, 0, 0, 0, 0, 0, 0, 0, 0, 0, 0, 0, 0, 0, 0,
            0, 0, 0, 0, 0, 0, 0, 0, 0, 0, 0, 0, 0, 0, 0, 0, 0, 0, 0, 0,
            0, 0, 0, 0, 0, 0, 0, 0, 0, 0, 0, 0, 0, 0, 0, 0, 0, 0, 0, 0,
            0, 0, 0, 0, 0, 0, 0, 0, 0, 0, 0, 0, 3278, 0, 0, 0, 0, 0, 0, 0,
            0, 0, 0, 0, 0, 0, 3378, 0, 0, 3307, 0, 0, 0, 0, 0, 0, 0, 0, 0, 0,
            0, 0, 0, 0, 0, 3310, 0, 0, 0, 3297, 0, 3307, 0, 0, 3310, 0, 0, 0, 0, 0,
            0, 0, 0, 0, 0, 0, 0, 0, 0, 0, 0, 0, 0, 3281, 0, 0, 0, 0, 0, 0,
            0, 0, 0, 0, 0, 3280, 0, 3310, 0, 0, 0, 0, 0, 0, 0, 0, 0, 0, 0, 0,
            0, 0, 0, 3378, 0, 0, 0, 0, 0, 3288, 0, 4394, 0, 0, 0, 3297, 0, 0, 0, 0,
            0, 0, 0, 0, 0, 0, 0, 3380, 0, 0, 0, 0, 3385, 0, 0, 0, 0, 0, 0, 0,
            0, 0, 0, 0, 0, 0, 0, 0, 0, 0, 0, 0, 0, 0, 0, 3380, 0, 0, 0, 0,
            0, 0, 0, 0, 0, 0, 0, 0, 0, 0, 0, 0, 0, 0, 0, 0, 0, 0, 0, 0,
            0, 0, 0, 0, 0, 0, 0, 0, 0, 3283, 0, 0, 3310, 0, 3286, 0, 0, 0, 0, 0,
            0, 0, 0, 3278, 0, 0, 0, 4800, 0, 0, 0, 0, 0, 0, 0, 0, 0, 0, 0, 0,
            0, 0, 0, 0, 0, 0, 0, 0, 3280, 3281, 0, 0, 0, 0, 3310, 0, 0, 0, 0, 0,
            0, 0, 0, 0, 0, 0, 0, 0, 0, 0, 0, 0, 0, 0, 0, 0, 0, 0, 0, 0,
            0, 0, 0, 0, 0, 0, 3281, 0, 3280, 0, 3330, 0, 0, 0, 0, 0, 0, 0, 0, 0,
            0, 0, 0, 0, 0, 0, 0, 0, 0, 0, 0, 0, 0, 0, 0, 0, 0, 0, 0, 0,
            0, 0, 0, 0, 0, 0, 0, 0, 0, 0, 0, 0, 0, 0, 0, 0, 0, 0, 0, 0,
            0, 0, 0, 0, 0, 0, 0, 0, 0, 0, 0, 0, 0, 0, 0, 0, 0, 0, 0, 0],
         "height":20,
         "id":7,
         "name":"deco0.25",
         "opacity":1,
         "type":"tilelayer",
         "visible":true,
         "width":20,
         "x":0,
         "y":0
        }, 
        {
         "data":[0, 0, 0, 0, 0, 0, 0, 0, 0, 0, 0, 0, 0, 0, 0, 0, 0, 0, 0, 0,
            0, 0, 0, 0, 0, 0, 0, 0, 0, 0, 0, 0, 0, 0, 0, 0, 0, 0, 0, 0,
            0, 0, 0, 0, 0, 0, 0, 0, 0, 0, 0, 0, 4723, 0, 0, 0, 6040, 0, 0, 0,
            0, 0, 0, 0, 0, 0, 0, 0, 0, 32, 0, 0, 0, 0, 0, 0, 0, 0, 0, 0,
            0, 0, 0, 0, 0, 0, 0, 0, 0, 0, 0, 0, 0, 0, 0, 0, 0, 0, 0, 0,
            0, 0, 0, 0, 0, 0, 0, 0, 0, 0, 0, 0, 0, 0, 0, 0, 0, 0, 0, 0,
            0, 0, 0, 0, 0, 0, 1511, 0, 0, 0, 0, 0, 1547, 0, 0, 0, 0, 0, 0, 0,
            0, 0, 0, 0, 3389, 0, 0, 0, 0, 0, 0, 0, 0, 0, 0, 0, 0, 0, 0, 0,
            0, 0, 0, 0, 0, 0, 0, 0, 0, 0, 0, 4738, 0, 0, 0, 0, 0, 0, 0, 0,
            0, 0, 0, 0, 0, 0, 4797, 0, 0, 0, 0, 0, 0, 0, 0, 0, 0, 0, 0, 0,
            0, 0, 0, 1547, 0, 0, 0, 0, 0, 1511, 0, 0, 0, 0, 1511, 0, 0, 0, 0, 0,
            0, 0, 0, 0, 0, 0, 3303, 0, 0, 0, 0, 0, 0, 0, 0, 0, 0, 0, 0, 0,
            0, 0, 0, 0, 0, 0, 0, 0, 0, 0, 0, 0, 0, 4727, 0, 0, 0, 6040, 0, 0,
            0, 0, 0, 4717, 3385, 0, 0, 0, 0, 0, 0, 0, 0, 0, 0, 0, 0, 0, 0, 0,
            0, 4724, 0, 0, 0, 0, 0, 0, 0, 0, 0, 0, 0, 0, 0, 0, 0, 0, 0, 0,
            0, 0, 0, 0, 0, 1511, 0, 0, 0, 0, 0, 0, 1547, 0, 0, 0, 0, 0, 0, 0,
            0, 0, 0, 0, 0, 0, 0, 0, 0, 4561, 0, 0, 0, 0, 0, 0, 0, 0, 0, 0,
            0, 0, 0, 0, 0, 0, 0, 0, 0, 0, 0, 0, 0, 0, 0, 0, 0, 0, 0, 0,
            0, 6040, 0, 0, 0, 0, 0, 0, 0, 0, 0, 0, 0, 0, 0, 0, 0, 0, 0, 0,
            0, 0, 0, 0, 0, 0, 0, 0, 0, 0, 0, 0, 0, 0, 0, 0, 0, 0, 0, 0],
         "height":20,
         "id":6,
         "name":"deco0.5",
         "opacity":1,
         "type":"tilelayer",
         "visible":true,
         "width":20,
         "x":0,
         "y":0
        }, 
        {
         "data":[0, 0, 0, 0, 0, 0, 0, 0, 0, 0, 0, 0, 0, 0, 0, 0, 0, 0, 0, 0,
            0, 0, 0, 0, 0, 0, 0, 0, 0, 0, 0, 0, 0, 0, 0, 0, 0, 0, 0, 0,
            0, 0, 0, 0, 0, 0, 0, 0, 0, 0, 0, 0, 0, 0, 0, 0, 0, 0, 0, 0,
            0, 0, 0, 0, 0, 0, 0, 0, 0, 0, 0, 0, 0, 0, 0, 0, 0, 0, 0, 0,
            0, 0, 0, 0, 0, 0, 0, 0, 0, 0, 0, 0, 0, 0, 0, 0, 0, 0, 0, 0,
            0, 0, 0, 0, 0, 0, 0, 0, 0, 0, 0, 0, 0, 0, 0, 0, 0, 0, 0, 0,
            0, 0, 0, 0, 0, 0, 0, 0, 0, 0, 0, 0, 0, 0, 0, 0, 0, 0, 0, 0,
            0, 0, 0, 0, 0, 0, 0, 0, 0, 0, 0, 0, 0, 0, 0, 0, 0, 0, 0, 0,
            0, 0, 0, 0, 0, 0, 0, 0, 0, 0, 0, 0, 0, 0, 0, 0, 0, 0, 0, 0,
            0, 0, 0, 0, 0, 0, 0, 0, 0, 0, 0, 0, 0, 0, 0, 0, 0, 0, 0, 0,
            0, 0, 0, 0, 0, 0, 0, 0, 0, 858, 0, 0, 0, 0, 0, 0, 0, 0, 0, 0,
            0, 0, 0, 0, 0, 0, 0, 0, 0, 0, 0, 0, 0, 0, 0, 0, 0, 0, 0, 0,
            0, 0, 0, 0, 0, 0, 0, 0, 0, 0, 0, 0, 0, 0, 0, 0, 0, 0, 0, 0,
            0, 0, 0, 0, 0, 0, 0, 0, 0, 0, 0, 0, 0, 0, 0, 0, 0, 0, 0, 0,
            0, 0, 0, 0, 0, 0, 0, 0, 0, 0, 0, 0, 0, 0, 0, 0, 0, 0, 0, 0,
            0, 0, 0, 0, 0, 0, 0, 0, 0, 0, 0, 0, 0, 0, 0, 0, 0, 0, 0, 0,
            0, 0, 0, 0, 0, 0, 0, 0, 0, 0, 0, 0, 0, 0, 0, 0, 0, 0, 0, 0,
            0, 0, 0, 0, 0, 0, 0, 0, 0, 0, 0, 0, 0, 0, 0, 0, 0, 0, 0, 0,
            0, 0, 0, 0, 0, 0, 0, 0, 0, 0, 0, 0, 0, 0, 0, 0, 0, 0, 0, 0,
            0, 0, 0, 0, 0, 0, 0, 0, 0, 0, 0, 0, 0, 0, 0, 0, 0, 0, 0, 0],
         "height":20,
         "id":3,
         "name":"deco",
         "opacity":1,
         "type":"tilelayer",
         "visible":true,
         "width":20,
         "x":0,
         "y":0
        }, 
        {
         "draworder":"topdown",
         "id":9,
         "name":"reference",
         "objects":[
                {
                 "height":0,
                 "id":18,
                 "name":"purgatory",
                 "point":true,
                 "rotation":0,
                 "type":"",
                 "visible":true,
                 "width":0,
                 "x":159.270603720949,
                 "y":228.852222942575
                }],
         "opacity":1,
         "type":"objectgroup",
         "visible":true,
         "x":0,
         "y":0
        }, 
        {
         "draworder":"topdown",
         "id":10,
         "name":"triggers",
         "objects":[
                {
                 "height":279.224376731302,
                 "id":19,
                 "name":"",
                 "rotation":0,
                 "type":"respawn",
                 "visible":true,
                 "width":294.274768668592,
                 "x":11.8818883715448,
                 "y":24.5559026345258
                }, 
                {
                 "height":33.5,
                 "id":20,
                 "name":"",
                 "properties":[
                        {
                         "name":"destMapName",
                         "type":"string",
                         "value":"UBCbattle"
                        }, 
                        {
                         "name":"destReference",
                         "type":"string",
                         "value":"2respawn"
                        }],
                 "rotation":0,
                 "type":"mapDoor",
                 "visible":true,
                 "width":34,
                 "x":354.5,
                 "y":132
                }],
         "opacity":1,
         "type":"objectgroup",
         "visible":true,
         "x":0,
         "y":0
        }, 
        {
         "draworder":"topdown",
         "id":8,
         "name":"sprites",
         "objects":[],
         "opacity":1,
         "type":"objectgroup",
         "visible":true,
         "x":0,
         "y":0
        }, 
        {
         "draworder":"topdown",
         "id":4,
         "name":"outOfBounds",
         "objects":[
                {
                 "height":48.6666666666667,
                 "id":1,
                 "name":"",
                 "rotation":0,
                 "type":"",
                 "visible":true,
                 "width":227.666666666667,
                 "x":95.3333333333333,
                 "y":-2
                }, 
                {
                 "height":66,
                 "id":2,
                 "name":"",
                 "rotation":0,
                 "type":"",
                 "visible":true,
                 "width":107,
                 "x":-11.6666666666667,
                 "y":-2.66666666666667
                }, 
                {
                 "height":30.3333333333333,
                 "id":3,
                 "name":"",
                 "rotation":0,
                 "type":"",
                 "visible":true,
                 "width":99.3333333333333,
                 "x":-20,
                 "y":50
                }, 
                {
                 "height":30,
                 "id":4,
                 "name":"",
                 "rotation":0,
                 "type":"",
                 "visible":true,
                 "width":95,
                 "x":-30.6666666666667,
                 "y":67
                }, 
                {
                 "height":229,
                 "id":5,
                 "name":"",
                 "rotation":0,
                 "type":"",
                 "visible":true,
                 "width":50.6666666666667,
                 "x":-3.33333333333334,
                 "y":97
                }, 
                {
                 "height":104,
                 "id":6,
                 "name":"",
                 "rotation":0,
                 "type":"",
                 "visible":true,
                 "width":17.6666666666667,
                 "x":47,
                 "y":222.666666666667
                }, 
                {
                 "height":90.6666666666666,
                 "id":7,
                 "name":"",
                 "rotation":0,
                 "type":"",
                 "visible":true,
                 "width":16.3333333333333,
                 "x":63.3333333333333,
                 "y":239
                }, 
                {
                 "height":79,
                 "id":8,
                 "name":"",
                 "rotation":0,
                 "type":"",
                 "visible":true,
                 "width":17,
                 "x":79,
                 "y":255.333333333333
                }, 
                {
                 "height":52.3333333333334,
                 "id":9,
                 "name":"",
                 "rotation":0,
                 "type":"",
                 "visible":true,
                 "width":233.666666666667,
                 "x":91.3333333333333,
                 "y":271.666666666667
                }, 
                {
                 "height":29.6666666666667,
                 "id":10,
                 "name":"",
                 "rotation":0,
                 "type":"",
                 "visible":true,
                 "width":100.666666666667,
                 "x":225.333333333333,
                 "y":256.333333333333
                }, 
                {
                 "height":24.3333333333333,
                 "id":11,
                 "name":"",
                 "rotation":0,
                 "type":"",
                 "visible":true,
                 "width":90,
                 "x":240.666666666667,
                 "y":240.666666666667
                }, 
                {
                 "height":32,
                 "id":12,
                 "name":"",
                 "rotation":0,
                 "type":"",
                 "visible":true,
                 "width":79.3333333333333,
                 "x":256.333333333333,
                 "y":224.333333333333
                }, 
                {
                 "height":18.3333333333333,
                 "id":13,
                 "name":"",
                 "rotation":0,
                 "type":"",
                 "visible":true,
                 "width":100.333333333333,
                 "x":223.666666666667,
                 "y":46.6666666666667
                }, 
                {
                 "height":15,
                 "id":14,
                 "name":"",
                 "rotation":0,
                 "type":"",
                 "visible":true,
                 "width":92.3333333333333,
                 "x":239.666666666667,
                 "y":64.6666666666667
                }, 
                {
                 "height":15.6666666666667,
                 "id":15,
                 "name":"",
                 "rotation":0,
                 "type":"",
                 "visible":true,
                 "width":73.6666666666666,
                 "x":256,
                 "y":79
                }, 
                {
                 "height":150,
                 "id":16,
                 "name":"",
                 "rotation":0,
                 "type":"",
                 "visible":true,
                 "width":65.6666666666667,
                 "x":272.333333333333,
                 "y":94
                }],
         "opacity":1,
         "type":"objectgroup",
         "visible":true,
         "x":0,
         "y":0
        }],
 "nextlayerid":11,
 "nextobjectid":21,
 "orientation":"orthogonal",
 "renderorder":"right-down",
 "tiledversion":"1.8.5",
 "tileheight":16,
 "tilesets":[
        {
         "firstgid":1,
         "source":"..\/..\/tilesets\/dungeon2.json"
        }, 
        {
         "firstgid":6081,
         "source":"..\/..\/tilesets\/dungeon216x16.json"
        }, 
        {
         "firstgid":30401,
         "source":"..\/..\/tilesets\/andre.json"
        }, 
        {
         "firstgid":30402,
         "source":"..\/..\/tilesets\/eric.json"
        }, 
        {
         "firstgid":30403,
         "source":"..\/..\/tilesets\/leslie.json"
        }, 
        {
         "firstgid":30404,
         "source":"..\/..\/tilesets\/Terrain and Outside.json"
        }],
 "tilewidth":16,
 "type":"map",
 "version":"1.8",
 "width":20
}